ImputeHiFI_Algorithm.py
ImputeHiFI_Algorithm_no_HiC.py
function_Run_ImputeHiFI.py
function_basic.py
ImputeHiFI-0.1.3.dist-info/LICENSE
ImputeHiFI-0.1.3.dist-info/METADATA
ImputeHiFI-0.1.3.dist-info/WHEEL
ImputeHiFI-0.1.3.dist-info/top_level.txt
ImputeHiFI-0.1.3.dist-info/RECORD
