Metadata-Version: 2.1
Name: ImputeHiFI
Version: 0.1.3
License-File: LICENSE
Requires-Dist: anyio (==4.2.0)
Requires-Dist: arrow (==1.3.0)
Requires-Dist: asciitree (==0.3.3)
Requires-Dist: async-lru (==2.0.4)
Requires-Dist: attrs (==23.2.0)
Requires-Dist: Babel (==2.14.0)
Requires-Dist: blinker (==1.4)
Requires-Dist: brotlipy (==0.7.0)
Requires-Dist: certifi (==2023.7.22)
Requires-Dist: comm (==0.2.1)
Requires-Dist: Cython (==0.29.35)
Requires-Dist: cytoolz (==0.11.2)
Requires-Dist: dgl (==0.8.2)
Requires-Dist: et-xmlfile (==1.1.0)
Requires-Dist: exceptiongroup (==1.2.0)
Requires-Dist: fonttools (==4.25.0)
Requires-Dist: fqdn (==1.5.1)
Requires-Dist: HeapDict (==1.0.1)
Requires-Dist: igraph (==0.10.4)
Requires-Dist: ipywidgets (==8.1.1)
Requires-Dist: isoduration (==20.11.0)
Requires-Dist: json5 (==0.9.14)
Requires-Dist: jsonpointer (==2.4)
Requires-Dist: jsonschema (==4.21.1)
Requires-Dist: jsonschema-specifications (==2023.12.1)
Requires-Dist: jupyter (==1.0.0)
Requires-Dist: jupyter-console (==6.6.3)
Requires-Dist: jupyter-events (==0.9.0)
Requires-Dist: jupyter-lsp (==2.2.2)
Requires-Dist: jupyter-client (==8.6.0)
Requires-Dist: jupyter-core (==5.7.0)
Requires-Dist: jupyter-server (==2.12.5)
Requires-Dist: jupyter-server-terminals (==0.5.2)
Requires-Dist: jupyterlab (==4.0.11)
Requires-Dist: jupyterlab-widgets (==3.0.9)
Requires-Dist: jupyterlab-server (==2.25.2)
Requires-Dist: leidenalg (==0.9.1)
Requires-Dist: llvmlite (==0.38.0)
Requires-Dist: loess (==2.0.11)
Requires-Dist: loompy (==3.0.7)
Requires-Dist: louvain (==0.8.0)
Requires-Dist: mkl-fft (==1.3.1)
Requires-Dist: mkl-service (==2.4.0)
Requires-Dist: munkres (==1.1.4)
Requires-Dist: nglview (==3.1.1)
Requires-Dist: notebook (==7.0.7)
Requires-Dist: notebook-shim (==0.2.3)
Requires-Dist: numpy (==1.21.5)
Requires-Dist: numpy-groupies (==0.9.20)
Requires-Dist: overrides (==7.6.0)
Requires-Dist: pandas (==1.4.2)
Requires-Dist: parse (==1.19.0)
Requires-Dist: patsy (==0.5.2)
Requires-Dist: Pillow (==9.0.1)
Requires-Dist: platformdirs (==4.1.0)
Requires-Dist: plotbin (==3.1.5)
Requires-Dist: prompt-toolkit (==3.0.43)
Requires-Dist: protobuf (==3.20.1)
Requires-Dist: psutil (==5.9.1)
Requires-Dist: pyasn1-modules (==0.2.8)
Requires-Dist: pybedtools (==0.8.2)
Requires-Dist: pynvml (==8.0.4)
Requires-Dist: pypairix (==0.3.7)
Requires-Dist: pyrle (==0.0.34)
Requires-Dist: pysam (==0.19.1)
Requires-Dist: python-igraph (==0.10.4)
Requires-Dist: python-json-logger (==2.0.7)
Requires-Dist: pytorch-ignite (==0.4.4)
Requires-Dist: pytz (==2021.3)
Requires-Dist: PyYAML (==5.4.1)
Requires-Dist: pyzmq (==25.1.2)
Requires-Dist: qtconsole (==5.5.1)
Requires-Dist: QtPy (==2.4.1)
Requires-Dist: referencing (==0.32.1)
Requires-Dist: requests (==2.31.0)
Requires-Dist: requests-oauthlib (==1.3.0)
Requires-Dist: rfc3339-validator (==0.1.4)
Requires-Dist: rfc3986-validator (==0.1.1)
Requires-Dist: rpds-py (==0.17.1)
Requires-Dist: scikit-misc (==0.1.4)
Requires-Dist: scvelo (==0.2.5)
Requires-Dist: Send2Trash (==1.8.2)
Requires-Dist: sip (==4.19.13)
Requires-Dist: sniffio (==1.3.0)
Requires-Dist: sorted-nearest (==0.0.33)
Requires-Dist: sparse (==0.13.0)
Requires-Dist: tensorboard-plugin-wit (==1.6.0)
Requires-Dist: tomli (==2.0.1)
Requires-Dist: torch (==1.10.1)
Requires-Dist: torchaudio (==0.10.1)
Requires-Dist: torchvision (==0.11.2)
Requires-Dist: tornado (==6.4)
Requires-Dist: traitlets (==5.14.1)
Requires-Dist: types-python-dateutil (==2.8.19.20240106)
Requires-Dist: uri-template (==1.3.0)
Requires-Dist: webcolors (==1.13)
Requires-Dist: webencodings (==0.5.1)
Requires-Dist: websocket-client (==1.7.0)
Requires-Dist: widgetsnbextension (==4.0.9)
Requires-Dist: portalocker (==2.4.0)
Requires-Dist: scanpy (==1.9.1)
Requires-Dist: scipy (==1.7.3)
Requires-Dist: matplotlib (==3.5.1)
Requires-Dist: seaborn (==0.11.2)
